cf_slumber.py
setup.py
cf_slumber.egg-info/PKG-INFO
cf_slumber.egg-info/SOURCES.txt
cf_slumber.egg-info/dependency_links.txt
cf_slumber.egg-info/requires.txt
cf_slumber.egg-info/top_level.txt