Metadata-Version: 1.0
Name: cf-slumber
Version: 0.3
Summary: CloudFoundry client based on Slumber
Home-page: https://github.com/sorenh/cf_slumber
Author: Soren Hansen
Author-email: soren@linux2go.dk
License: UNKNOWN
Platform: UNKNOWN
